pcf_toolkit/__init__.py
pcf_toolkit/cli.py
pcf_toolkit/cli_helpers.py
pcf_toolkit/io.py
pcf_toolkit/json_schema.py
pcf_toolkit/models.py
pcf_toolkit/py.typed
pcf_toolkit/rich_help.py
pcf_toolkit/schema_snapshot.py
pcf_toolkit/types.py
pcf_toolkit/xml.py
pcf_toolkit/xml_import.py
pcf_toolkit/data/__init__.py
pcf_toolkit/data/manifest.schema.json
pcf_toolkit/data/schema_snapshot.json
pcf_toolkit/data/spec_raw.json
pcf_toolkit/proxy/__init__.py
pcf_toolkit/proxy/browser.py
pcf_toolkit/proxy/cli.py
pcf_toolkit/proxy/config.py
pcf_toolkit/proxy/doctor.py
pcf_toolkit/proxy/mitm.py
pcf_toolkit/proxy/server.py
pcf_toolkit/proxy/addons/__init__.py
pcf_toolkit/proxy/addons/redirect_bundle.py
pcf_toolkit-0.2.6.dist-info/licenses/LICENSE.md
pcf_toolkit-0.2.6.dist-info/METADATA
pcf_toolkit-0.2.6.dist-info/WHEEL
pcf_toolkit-0.2.6.dist-info/entry_points.txt
pcf_toolkit-0.2.6.dist-info/top_level.txt
pcf_toolkit-0.2.6.dist-info/RECORD
