Metadata-Version: 2.4
Name: pcf-toolkit
Version: 0.2.6
Summary: PCF toolkit CLI for manifest authoring and local proxy development.
Author-email: Vectorfy Co - Andrew M <contact@vectorfy.co>
License: <div align="center">
Project-URL: homepage, https://docs.pcf-toolkit.vectorfy.co
Project-URL: repository, https://github.com/vectorfy-co/pcf-toolkit
Project-URL: issues, https://github.com/vectorfy-co/pcf-toolkit/issues
Keywords: pcf,power-apps,power-platform,manifest,xml,yaml,proxy,toolkit
Classifier: Development Status :: 4 - Beta
Classifier: Intended Audience :: Developers
Classifier: Programming Language :: Python :: 3
Classifier: Programming Language :: Python :: 3.13
Classifier: Topic :: Software Development :: Build Tools
Requires-Python: >=3.13
License-File: LICENSE.md
Requires-Dist: pydantic>=2.6
Requires-Dist: typer>=0.12
Requires-Dist: pyyaml>=6.0
Requires-Dist: questionary>=2.0
Provides-Extra: dev
Requires-Dist: pytest>=7.4; extra == "dev"
Requires-Dist: pytest-cov>=5.0; extra == "dev"
Requires-Dist: playwright>=1.40; extra == "dev"
Requires-Dist: ruff>=0.6; extra == "dev"
Requires-Dist: gitpython>=3.1.46; extra == "dev"
Requires-Dist: pydantic-settings>=2.12.0; extra == "dev"
Requires-Dist: tomlkit>=0.14.0; extra == "dev"
Requires-Dist: rich>=14.2.0; extra == "dev"
Requires-Dist: packaging>=25.0; extra == "dev"
Provides-Extra: proxy
Requires-Dist: mitmproxy>=10.0; extra == "proxy"
Dynamic: license-file
